{
  "TopPageModule": "PurchaseOrders",
  "Name": "Main",
  "Description": "",
  "Left": {
    "IsVisible": false,
    "Home": {
      "Type": "Text",
      "Text": "Home",
      "Icon": "",
      "ResourcePath": ""
    },
    "Links": [],
    "Foreground": "#ffffff",
    "BackgroundStart": "#052767",
    "BackgroundEnd": "#3a0647"
  },
  "Right": {
    "IsVisible": false,
    "Home": {
      "Type": "None",
      "Text": "",
      "Icon": "",
      "ResourcePath": ""
    },
    "Links": [],
    "Foreground": "#ffffff",
    "BackgroundStart": "#052767",
    "BackgroundEnd": "#3a0647"
  },
  "Header": {
    "IsVisible": true,
    "Foreground": "#ffffff",
    "Background": "#0d6efd",
    "Home": {
      "Type": "Text",
      "Text": "SAP",
      "Icon": "",
      "ResourcePath": ""
    },
    "Links": [
      {
        "Title": "PurchaseOrders",
        "Icon": "",
        "PageFrame": "",
        "Module": "PurchaseOrders"
      },
      {
        "Title": "Sepmra",
        "Icon": "",
        "PageFrame": "",
        "Module": "Sepmra"
      }
    ]
  },
  "OtherPages": []
}