{
  "Name": "AITest2",
  "DisplayName": "",
  "PageTitle": "Invoice",
  "DataSourceName": "",
  "DbTable": "",
  "CanCreate": true,
  "CanUpdate": true,
  "CanDelete": true,
  "CanBulkDataUpdate": false,
  "CanBulkDataDownload": false,
  "UseListPageSubmitButton": false,
  "Fields": [
    {
      "DbColumn": "",
      "IsMultiline": false,
      "Placeholder": "",
      "IsUpdateProtected": false,
      "IsSimpleSearchParameter": false,
      "OnSearchDataChanged": "",
      "DisplayName": "",
      "IsRequired": false,
      "OnDataChanged": "",
      "Name": "請求書番号",
      "TypeFullName": "Codeer.LowCode.Blazor.Repository.Design.TextFieldDesign"
    },
    {
      "LayoutName": "",
      "CanNavigateToDetail": false,
      "IsStriped": false,
      "DisplayName": "",
      "SearchCondition": {
        "SortFieldVariable": "",
        "SortDescending": false,
        "SelectFields": [],
        "ModuleName": "AITest2Child",
        "Condition": {
          "IsOrMatch": false,
          "Children": [],
          "Name": "",
          "TypeFullName": "Codeer.LowCode.Blazor.Repository.Match.MultiMatchCondition"
        }
      },
      "PagerPosition": "Bottom",
      "UseIndexSort": false,
      "DeleteTogether": true,
      "CanCreate": true,
      "CanUpdate": true,
      "CanDelete": true,
      "CanUserSort": true,
      "CanSelect": false,
      "OnDataChanged": "List_OnDataChanged",
      "OnSearchDataChanged": "",
      "OnSelectedIndexChanged": "",
      "OnSelectedIndexChanging": "",
      "Name": "List",
      "TypeFullName": "Codeer.LowCode.Blazor.Repository.Design.ListFieldDesign"
    },
    {
      "DataImportCompleted": "AITextAnalyzer_DataImportCompleted",
      "Name": "AITextAnalyzer",
      "TypeFullName": "Design.Samples.AIDocumentAnalyzer.AITextAnalyzerFieldDesign"
    },
    {
      "Placeholder": "",
      "Format": "",
      "DbColumn": "",
      "IsUpdateProtected": false,
      "IsSimpleSearchParameter": false,
      "OnSearchDataChanged": "",
      "DisplayName": "合計金額",
      "IsRequired": false,
      "OnDataChanged": "",
      "Name": "Total",
      "TypeFullName": "Codeer.LowCode.Blazor.Repository.Design.NumberFieldDesign"
    },
    {
      "Text": "",
      "Icon": "",
      "Style": "Default",
      "RelativeField": "請求書番号",
      "OnClick": "",
      "Name": "請求書番号Label",
      "TypeFullName": "Codeer.LowCode.Blazor.Repository.Design.LabelFieldDesign"
    },
    {
      "Text": "請求先情報",
      "Icon": "",
      "Style": "Default",
      "RelativeField": "",
      "OnClick": "",
      "Name": "Label",
      "TypeFullName": "Codeer.LowCode.Blazor.Repository.Design.LabelFieldDesign"
    },
    {
      "DbColumn": "",
      "IsMultiline": false,
      "Placeholder": "",
      "IsUpdateProtected": false,
      "IsSimpleSearchParameter": false,
      "OnSearchDataChanged": "",
      "DisplayName": "",
      "IsRequired": false,
      "OnDataChanged": "",
      "Name": "請求先会社名",
      "TypeFullName": "Codeer.LowCode.Blazor.Repository.Design.TextFieldDesign"
    },
    {
      "DbColumn": "",
      "IsMultiline": false,
      "Placeholder": "",
      "IsUpdateProtected": false,
      "IsSimpleSearchParameter": false,
      "OnSearchDataChanged": "",
      "DisplayName": "",
      "IsRequired": false,
      "OnDataChanged": "",
      "Name": "請求先担当者名",
      "TypeFullName": "Codeer.LowCode.Blazor.Repository.Design.TextFieldDesign"
    },
    {
      "DbColumn": "",
      "IsMultiline": false,
      "Placeholder": "",
      "IsUpdateProtected": false,
      "IsSimpleSearchParameter": false,
      "OnSearchDataChanged": "",
      "DisplayName": "",
      "IsRequired": false,
      "OnDataChanged": "",
      "Name": "請求先住所",
      "TypeFullName": "Codeer.LowCode.Blazor.Repository.Design.TextFieldDesign"
    },
    {
      "DbColumn": "",
      "IsMultiline": false,
      "Placeholder": "",
      "IsUpdateProtected": false,
      "IsSimpleSearchParameter": false,
      "OnSearchDataChanged": "",
      "DisplayName": "",
      "IsRequired": false,
      "OnDataChanged": "",
      "Name": "請求先電話番号",
      "TypeFullName": "Codeer.LowCode.Blazor.Repository.Design.TextFieldDesign"
    },
    {
      "Text": "",
      "Icon": "",
      "Style": "Default",
      "RelativeField": "Total",
      "OnClick": "",
      "Name": "TotalLabel",
      "TypeFullName": "Codeer.LowCode.Blazor.Repository.Design.LabelFieldDesign"
    },
    {
      "DbColumn": "",
      "IsMultiline": true,
      "Placeholder": "",
      "IsUpdateProtected": false,
      "IsSimpleSearchParameter": false,
      "OnSearchDataChanged": "",
      "DisplayName": "",
      "IsRequired": false,
      "OnDataChanged": "",
      "Name": "支払い情報",
      "TypeFullName": "Codeer.LowCode.Blazor.Repository.Design.TextFieldDesign"
    },
    {
      "DbColumn": "",
      "IsMultiline": true,
      "Placeholder": "",
      "IsUpdateProtected": false,
      "IsSimpleSearchParameter": false,
      "OnSearchDataChanged": "",
      "DisplayName": "",
      "IsRequired": false,
      "OnDataChanged": "",
      "Name": "備考",
      "TypeFullName": "Codeer.LowCode.Blazor.Repository.Design.TextFieldDesign"
    },
    {
      "Text": "",
      "Icon": "",
      "Style": "Default",
      "RelativeField": "支払い情報",
      "OnClick": "",
      "Name": "支払い情報Label",
      "TypeFullName": "Codeer.LowCode.Blazor.Repository.Design.LabelFieldDesign"
    },
    {
      "Text": "",
      "Icon": "",
      "Style": "Default",
      "RelativeField": "備考",
      "OnClick": "",
      "Name": "備考Label",
      "TypeFullName": "Codeer.LowCode.Blazor.Repository.Design.LabelFieldDesign"
    }
  ],
  "UserWriteCondition": {
    "ModuleName": ""
  },
  "UserReadCondition": {
    "ModuleName": ""
  },
  "DataWriteCondition": {
    "ModuleName": ""
  },
  "DataReadCondition": {
    "ModuleName": ""
  },
  "DetailLayouts": {
    "": {
      "OnBeforeInitialization": "",
      "OnAfterInitialization": "",
      "DataOnlyFields": [],
      "Layout": {
        "Name": "",
        "Padding": {},
        "IsBordered": false,
        "IsFlowLayout": false,
        "IsFillAvailable": false,
        "IsExpandable": false,
        "ExpanderLabel": "",
        "IsExpanderDefaultOpened": false,
        "Rows": [
          {
            "IsWrap": false,
            "Margin": {},
            "GridRowType": "Normal",
            "BackgroundColor": "",
            "IsRowMarginRemoved": false,
            "Columns": [
              {
                "Layout": {
                  "FieldName": "請求書番号Label",
                  "FontFamily": "",
                  "Color": "",
                  "BackgroundColor": "",
                  "Name": "",
                  "TypeFullName": "Codeer.LowCode.Blazor.Repository.Design.FieldLayoutDesign"
                },
                "Width": 120,
                "Padding": {},
                "BackgroundColor": "",
                "Border": "None",
                "VerticalAlignment": "Middle",
                "CanResize": false
              },
              {
                "Layout": {
                  "FieldName": "請求書番号",
                  "FontFamily": "",
                  "Color": "",
                  "BackgroundColor": "",
                  "Name": "",
                  "TypeFullName": "Codeer.LowCode.Blazor.Repository.Design.FieldLayoutDesign"
                },
                "Padding": {},
                "BackgroundColor": "",
                "Border": "None",
                "CanResize": false
              }
            ]
          },
          {
            "IsWrap": false,
            "Margin": {},
            "GridRowType": "Normal",
            "BackgroundColor": "",
            "IsRowMarginRemoved": false,
            "Columns": [
              {
                "Layout": {
                  "Name": "",
                  "Padding": {},
                  "IsBordered": true,
                  "IsFlowLayout": false,
                  "IsFillAvailable": false,
                  "IsExpandable": false,
                  "ExpanderLabel": "",
                  "IsExpanderDefaultOpened": false,
                  "Rows": [
                    {
                      "IsWrap": false,
                      "Margin": {
                        "Bottom": 0
                      },
                      "GridRowType": "Normal",
                      "BackgroundColor": "",
                      "IsRowMarginRemoved": true,
                      "Columns": [
                        {
                          "Layout": {
                            "FieldName": "Label",
                            "FontFamily": "",
                            "Color": "",
                            "BackgroundColor": "",
                            "Name": "",
                            "TypeFullName": "Codeer.LowCode.Blazor.Repository.Design.FieldLayoutDesign"
                          },
                          "Padding": {},
                          "BackgroundColor": "",
                          "Border": "None",
                          "CanResize": false
                        }
                      ]
                    },
                    {
                      "IsWrap": false,
                      "Margin": {},
                      "GridRowType": "Normal",
                      "BackgroundColor": "",
                      "IsRowMarginRemoved": false,
                      "Columns": [
                        {
                          "Width": 110,
                          "Padding": {},
                          "BackgroundColor": "",
                          "Border": "None",
                          "CanResize": false
                        },
                        {
                          "Layout": {
                            "FieldName": "請求先会社名",
                            "FontFamily": "",
                            "Color": "",
                            "BackgroundColor": "",
                            "Name": "",
                            "TypeFullName": "Codeer.LowCode.Blazor.Repository.Design.FieldLayoutDesign"
                          },
                          "Padding": {},
                          "BackgroundColor": "",
                          "Border": "None",
                          "CanResize": false
                        }
                      ]
                    },
                    {
                      "IsWrap": false,
                      "Margin": {},
                      "GridRowType": "Normal",
                      "BackgroundColor": "",
                      "IsRowMarginRemoved": false,
                      "Columns": [
                        {
                          "Width": 110,
                          "Padding": {},
                          "BackgroundColor": "",
                          "Border": "None",
                          "CanResize": false
                        },
                        {
                          "Layout": {
                            "FieldName": "請求先担当者名",
                            "FontFamily": "",
                            "Color": "",
                            "BackgroundColor": "",
                            "Name": "",
                            "TypeFullName": "Codeer.LowCode.Blazor.Repository.Design.FieldLayoutDesign"
                          },
                          "Padding": {},
                          "BackgroundColor": "",
                          "Border": "None",
                          "CanResize": false
                        }
                      ]
                    },
                    {
                      "IsWrap": false,
                      "Margin": {},
                      "GridRowType": "Normal",
                      "BackgroundColor": "",
                      "IsRowMarginRemoved": false,
                      "Columns": [
                        {
                          "Width": 110,
                          "Padding": {},
                          "BackgroundColor": "",
                          "Border": "None",
                          "CanResize": false
                        },
                        {
                          "Layout": {
                            "FieldName": "請求先住所",
                            "FontFamily": "",
                            "Color": "",
                            "BackgroundColor": "",
                            "Name": "",
                            "TypeFullName": "Codeer.LowCode.Blazor.Repository.Design.FieldLayoutDesign"
                          },
                          "Padding": {},
                          "BackgroundColor": "",
                          "Border": "None",
                          "CanResize": false
                        }
                      ]
                    },
                    {
                      "IsWrap": false,
                      "Margin": {},
                      "GridRowType": "Normal",
                      "BackgroundColor": "",
                      "IsRowMarginRemoved": false,
                      "Columns": [
                        {
                          "Width": 110,
                          "Padding": {},
                          "BackgroundColor": "",
                          "Border": "None",
                          "CanResize": false
                        },
                        {
                          "Layout": {
                            "FieldName": "請求先電話番号",
                            "FontFamily": "",
                            "Color": "",
                            "BackgroundColor": "",
                            "Name": "",
                            "TypeFullName": "Codeer.LowCode.Blazor.Repository.Design.FieldLayoutDesign"
                          },
                          "Padding": {},
                          "BackgroundColor": "",
                          "Border": "None",
                          "CanResize": false
                        }
                      ]
                    }
                  ],
                  "TypeFullName": "Codeer.LowCode.Blazor.Repository.Design.GridLayoutDesign"
                },
                "Padding": {},
                "BackgroundColor": "",
                "Border": "None",
                "CanResize": false
              }
            ]
          },
          {
            "IsWrap": false,
            "Margin": {},
            "GridRowType": "Normal",
            "BackgroundColor": "",
            "IsRowMarginRemoved": false,
            "Columns": [
              {
                "Padding": {},
                "BackgroundColor": "",
                "Border": "None",
                "CanResize": false
              }
            ]
          },
          {
            "IsWrap": false,
            "Margin": {},
            "GridRowType": "Normal",
            "BackgroundColor": "",
            "IsRowMarginRemoved": false,
            "Columns": [
              {
                "Layout": {
                  "FieldName": "List",
                  "FontFamily": "",
                  "Color": "",
                  "BackgroundColor": "",
                  "Name": "",
                  "TypeFullName": "Codeer.LowCode.Blazor.Repository.Design.FieldLayoutDesign"
                },
                "Padding": {},
                "BackgroundColor": "",
                "Border": "None",
                "CanResize": false
              }
            ]
          },
          {
            "IsWrap": false,
            "Margin": {},
            "GridRowType": "Normal",
            "BackgroundColor": "",
            "IsRowMarginRemoved": false,
            "Columns": [
              {
                "Layout": {
                  "FieldName": "TotalLabel",
                  "FontFamily": "",
                  "Color": "",
                  "BackgroundColor": "",
                  "Name": "",
                  "TypeFullName": "Codeer.LowCode.Blazor.Repository.Design.FieldLayoutDesign"
                },
                "Width": 120,
                "Padding": {},
                "BackgroundColor": "",
                "Border": "None",
                "VerticalAlignment": "Middle",
                "CanResize": false
              },
              {
                "Layout": {
                  "FieldName": "Total",
                  "FontFamily": "",
                  "Color": "",
                  "BackgroundColor": "",
                  "Name": "",
                  "TypeFullName": "Codeer.LowCode.Blazor.Repository.Design.FieldLayoutDesign"
                },
                "Padding": {},
                "BackgroundColor": "",
                "Border": "None",
                "CanResize": false
              }
            ]
          },
          {
            "IsWrap": false,
            "Margin": {},
            "GridRowType": "Normal",
            "BackgroundColor": "",
            "IsRowMarginRemoved": false,
            "Columns": [
              {
                "Layout": {
                  "FieldName": "支払い情報Label",
                  "FontFamily": "",
                  "Color": "",
                  "BackgroundColor": "",
                  "Name": "",
                  "TypeFullName": "Codeer.LowCode.Blazor.Repository.Design.FieldLayoutDesign"
                },
                "Width": 120,
                "Padding": {},
                "BackgroundColor": "",
                "Border": "None",
                "VerticalAlignment": "Middle",
                "CanResize": false
              },
              {
                "Layout": {
                  "FieldName": "支払い情報",
                  "FontFamily": "",
                  "Color": "",
                  "BackgroundColor": "",
                  "Name": "",
                  "TypeFullName": "Codeer.LowCode.Blazor.Repository.Design.FieldLayoutDesign"
                },
                "Padding": {},
                "BackgroundColor": "",
                "Border": "None",
                "CanResize": false
              }
            ]
          },
          {
            "IsWrap": false,
            "Margin": {},
            "GridRowType": "Normal",
            "BackgroundColor": "",
            "IsRowMarginRemoved": false,
            "Columns": [
              {
                "Layout": {
                  "FieldName": "備考Label",
                  "FontFamily": "",
                  "Color": "",
                  "BackgroundColor": "",
                  "Name": "",
                  "TypeFullName": "Codeer.LowCode.Blazor.Repository.Design.FieldLayoutDesign"
                },
                "Width": 120,
                "Padding": {},
                "BackgroundColor": "",
                "Border": "None",
                "VerticalAlignment": "Middle",
                "CanResize": false
              },
              {
                "Layout": {
                  "FieldName": "備考",
                  "FontFamily": "",
                  "Color": "",
                  "BackgroundColor": "",
                  "Name": "",
                  "TypeFullName": "Codeer.LowCode.Blazor.Repository.Design.FieldLayoutDesign"
                },
                "Padding": {},
                "BackgroundColor": "",
                "Border": "None",
                "CanResize": false
              }
            ]
          },
          {
            "IsWrap": false,
            "Margin": {},
            "GridRowType": "Normal",
            "BackgroundColor": "",
            "IsRowMarginRemoved": false,
            "Columns": [
              {
                "Layout": {
                  "FieldName": "AITextAnalyzer",
                  "FontFamily": "",
                  "Color": "",
                  "BackgroundColor": "",
                  "Name": "",
                  "TypeFullName": "Codeer.LowCode.Blazor.Repository.Design.FieldLayoutDesign"
                },
                "Padding": {},
                "BackgroundColor": "",
                "Border": "None",
                "CanResize": false
              }
            ]
          }
        ],
        "TypeFullName": "Codeer.LowCode.Blazor.Repository.Design.GridLayoutDesign"
      }
    }
  },
  "ListLayouts": {
    "": {
      "HeaderTitle": "",
      "DataOnlyFields": [],
      "OnBeforeInitialization": "",
      "OnAfterInitialization": "",
      "Elements": [
        [
          {
            "FieldName": "",
            "Label": "",
            "ColumnSpan": 1,
            "RowSpan": 1,
            "TextWrap": "Unset",
            "CanResize": false,
            "CanUserSort": true,
            "FontFamily": "",
            "Color": "",
            "BackgroundColor": ""
          }
        ]
      ]
    }
  },
  "SearchLayouts": {
    "": {
      "OnSearchInitialization": "",
      "Layout": {
        "Operator": "And",
        "Name": "SearchGridLayout",
        "Padding": {},
        "IsBordered": false,
        "IsFlowLayout": false,
        "IsFillAvailable": false,
        "IsExpandable": true,
        "ExpanderLabel": "検索条件",
        "IsExpanderDefaultOpened": false,
        "Rows": [
          {
            "IsWrap": false,
            "Margin": {},
            "GridRowType": "Normal",
            "BackgroundColor": "",
            "IsRowMarginRemoved": false,
            "Columns": [
              {
                "Padding": {},
                "BackgroundColor": "",
                "Border": "None",
                "CanResize": false
              },
              {
                "Padding": {},
                "BackgroundColor": "",
                "Border": "None",
                "CanResize": false
              },
              {
                "Padding": {},
                "BackgroundColor": "",
                "Border": "None",
                "CanResize": false
              },
              {
                "Padding": {},
                "BackgroundColor": "",
                "Border": "None",
                "CanResize": false
              }
            ]
          }
        ],
        "TypeFullName": "Codeer.LowCode.Blazor.Repository.Design.SearchGridLayoutDesign"
      }
    }
  },
  "LinkFieldNames": [],
  "ListPageFieldDesign": {
    "LayoutName": "",
    "CanNavigateToDetail": true,
    "IsStriped": false,
    "DisplayName": "",
    "SearchCondition": {
      "LimitCount": 50,
      "SortFieldVariable": "",
      "SortDescending": false,
      "SelectFields": [],
      "ModuleName": ""
    },
    "PagerPosition": "Bottom",
    "UseIndexSort": false,
    "DeleteTogether": false,
    "CanCreate": false,
    "CanUpdate": false,
    "CanDelete": false,
    "CanUserSort": true,
    "CanSelect": false,
    "OnDataChanged": "",
    "OnSearchDataChanged": "",
    "OnSelectedIndexChanged": "",
    "OnSelectedIndexChanging": "",
    "Name": "",
    "TypeFullName": "Codeer.LowCode.Blazor.Repository.Design.ListFieldDesign"
  }
}