{
  "Name": "ChartSample",
  "DisplayName": "",
  "PageTitle": "",
  "DataSourceName": "",
  "DbTable": "",
  "CanCreate": true,
  "CanUpdate": true,
  "CanDelete": true,
  "CanBulkDataUpdate": false,
  "CanBulkDataDownload": false,
  "UseListPageSubmitButton": false,
  "Fields": [
    {
      "Keys": [],
      "XAxisTitle": "Year",
      "YAxisTitle": "TWh",
      "Height": "500px",
      "LayoutName": "",
      "DisplayName": "",
      "SearchCondition": {
        "SortFieldVariable": "Year.Value",
        "SortDescending": false,
        "SelectFields": [],
        "ModuleName": "ElectricPower",
        "Condition": {
          "IsOrMatch": false,
          "Children": [],
          "Name": "",
          "TypeFullName": "Codeer.LowCode.Blazor.Repository.Match.MultiMatchCondition"
        }
      },
      "PagerPosition": "Bottom",
      "UseIndexSort": false,
      "DeleteTogether": false,
      "CanCreate": false,
      "CanUpdate": false,
      "CanDelete": false,
      "CanUserSort": true,
      "CanSelect": false,
      "OnDataChanged": "",
      "OnSearchDataChanged": "",
      "OnSelectedIndexChanged": "",
      "OnSelectedIndexChanging": "",
      "Name": "IgbLineChart",
      "TypeFullName": "LowCodeSamples.Client.Shared.Fields.IgbLineChartFieldDesign"
    }
  ],
  "UserWriteCondition": {
    "ModuleName": ""
  },
  "UserReadCondition": {
    "ModuleName": ""
  },
  "DataWriteCondition": {
    "ModuleName": ""
  },
  "DataReadCondition": {
    "ModuleName": ""
  },
  "DetailLayouts": {
    "": {
      "OnBeforeInitialization": "",
      "OnAfterInitialization": "",
      "DataOnlyFields": [],
      "Layout": {
        "Name": "",
        "Padding": {},
        "IsBordered": false,
        "IsFlowLayout": false,
        "IsFillAvailable": false,
        "IsExpandable": false,
        "ExpanderLabel": "",
        "IsExpanderDefaultOpened": false,
        "Rows": [
          {
            "IsWrap": false,
            "Margin": {},
            "GridRowType": "Normal",
            "BackgroundColor": "",
            "IsRowMarginRemoved": false,
            "Columns": [
              {
                "Layout": {
                  "FieldName": "IgbLineChart",
                  "FontFamily": "",
                  "Color": "",
                  "BackgroundColor": "",
                  "Name": "",
                  "TypeFullName": "Codeer.LowCode.Blazor.Repository.Design.FieldLayoutDesign"
                },
                "Padding": {},
                "BackgroundColor": "",
                "Border": "None",
                "CanResize": false
              }
            ]
          }
        ],
        "TypeFullName": "Codeer.LowCode.Blazor.Repository.Design.GridLayoutDesign"
      }
    }
  },
  "ListLayouts": {
    "": {
      "HeaderTitle": "",
      "DataOnlyFields": [],
      "OnBeforeInitialization": "",
      "OnAfterInitialization": "",
      "Elements": [
        [
          {
            "FieldName": "",
            "Label": "",
            "ColumnSpan": 1,
            "RowSpan": 1,
            "TextWrap": "Unset",
            "CanResize": false,
            "CanUserSort": true,
            "FontFamily": "",
            "Color": "",
            "BackgroundColor": ""
          }
        ]
      ]
    }
  },
  "SearchLayouts": {
    "": {
      "OnSearchInitialization": "",
      "Layout": {
        "Operator": "And",
        "Name": "SearchGridLayout",
        "Padding": {},
        "IsBordered": false,
        "IsFlowLayout": false,
        "IsFillAvailable": false,
        "IsExpandable": true,
        "ExpanderLabel": "検索条件",
        "IsExpanderDefaultOpened": false,
        "Rows": [
          {
            "IsWrap": false,
            "Margin": {},
            "GridRowType": "Normal",
            "BackgroundColor": "",
            "IsRowMarginRemoved": false,
            "Columns": [
              {
                "Padding": {},
                "BackgroundColor": "",
                "Border": "None",
                "CanResize": false
              },
              {
                "Padding": {},
                "BackgroundColor": "",
                "Border": "None",
                "CanResize": false
              },
              {
                "Padding": {},
                "BackgroundColor": "",
                "Border": "None",
                "CanResize": false
              },
              {
                "Padding": {},
                "BackgroundColor": "",
                "Border": "None",
                "CanResize": false
              }
            ]
          }
        ],
        "TypeFullName": "Codeer.LowCode.Blazor.Repository.Design.SearchGridLayoutDesign"
      }
    }
  },
  "LinkFieldNames": [],
  "ListPageFieldDesign": {
    "LayoutName": "",
    "CanNavigateToDetail": true,
    "IsStriped": false,
    "DisplayName": "",
    "SearchCondition": {
      "LimitCount": 50,
      "SortFieldVariable": "",
      "SortDescending": false,
      "SelectFields": [],
      "ModuleName": ""
    },
    "PagerPosition": "Bottom",
    "UseIndexSort": false,
    "DeleteTogether": false,
    "CanCreate": false,
    "CanUpdate": false,
    "CanDelete": false,
    "CanUserSort": true,
    "CanSelect": false,
    "OnDataChanged": "",
    "OnSearchDataChanged": "",
    "OnSelectedIndexChanged": "",
    "OnSelectedIndexChanging": "",
    "Name": "",
    "TypeFullName": "Codeer.LowCode.Blazor.Repository.Design.ListFieldDesign"
  }
}