{
  "Name": "ChartData",
  "DisplayName": "",
  "PageTitle": "",
  "DataSourceName": "SampleSQLite",
  "DbTable": "TestValues",
  "CanCreate": true,
  "CanUpdate": true,
  "CanDelete": true,
  "CanBulkDataUpdate": true,
  "CanBulkDataDownload": true,
  "Fields": [
    {
      "DbColumn": "Id",
      "Placeholder": "",
      "IsManualInput": false,
      "CompositeIdVariables": [],
      "CompositeIdSeparator": "",
      "IsUpdateProtected": false,
      "OnSearchDataChanged": "",
      "DisplayName": "",
      "IsRequired": false,
      "OnDataChanged": "",
      "Name": "Id",
      "TypeFullName": "Codeer.LowCode.Blazor.Repository.Design.IdFieldDesign"
    },
    {
      "Placeholder": "",
      "Format": "",
      "DbColumn": "A",
      "IsUpdateProtected": false,
      "OnSearchDataChanged": "",
      "DisplayName": "",
      "IsRequired": false,
      "OnDataChanged": "",
      "Name": "A",
      "TypeFullName": "Codeer.LowCode.Blazor.Repository.Design.NumberFieldDesign"
    },
    {
      "Placeholder": "",
      "Format": "",
      "DbColumn": "B",
      "IsUpdateProtected": false,
      "OnSearchDataChanged": "",
      "DisplayName": "",
      "IsRequired": false,
      "OnDataChanged": "",
      "Name": "B",
      "TypeFullName": "Codeer.LowCode.Blazor.Repository.Design.NumberFieldDesign"
    },
    {
      "Placeholder": "",
      "Format": "",
      "DbColumn": "C",
      "IsUpdateProtected": false,
      "OnSearchDataChanged": "",
      "DisplayName": "",
      "IsRequired": false,
      "OnDataChanged": "",
      "Name": "C",
      "TypeFullName": "Codeer.LowCode.Blazor.Repository.Design.NumberFieldDesign"
    },
    {
      "Text": "Valuds",
      "Style": "H1",
      "RelativeField": "",
      "Name": "Header",
      "TypeFullName": "Codeer.LowCode.Blazor.Repository.Design.LabelFieldDesign"
    },
    {
      "Text": "",
      "Style": "Default",
      "RelativeField": "A",
      "Name": "ALabel",
      "TypeFullName": "Codeer.LowCode.Blazor.Repository.Design.LabelFieldDesign"
    },
    {
      "Text": "",
      "Style": "Default",
      "RelativeField": "B",
      "Name": "BLabel",
      "TypeFullName": "Codeer.LowCode.Blazor.Repository.Design.LabelFieldDesign"
    },
    {
      "Text": "",
      "Style": "Default",
      "RelativeField": "C",
      "Name": "CLabel",
      "TypeFullName": "Codeer.LowCode.Blazor.Repository.Design.LabelFieldDesign"
    },
    {
      "Text": "Submit",
      "Icon": "",
      "Name": "Submit",
      "TypeFullName": "Codeer.LowCode.Blazor.Repository.Design.SubmitButtonFieldDesign"
    }
  ],
  "UserWriteCondition": {
    "ModuleName": ""
  },
  "UserReadCondition": {
    "ModuleName": ""
  },
  "DataWriteCondition": {
    "ModuleName": ""
  },
  "DataReadCondition": {
    "ModuleName": ""
  },
  "OnTransaction": "",
  "DetailLayouts": {
    "": {
      "OnBeforeInitialization": "",
      "OnAfterInitialization": "",
      "DataOnlyFields": [],
      "Layout": {
        "Name": "",
        "IsBordered": false,
        "IsFlowLayout": false,
        "IsFillAvailable": false,
        "IsExpandable": false,
        "ExpanderLabel": "",
        "IsExpanderDefaultOpened": false,
        "Rows": [
          {
            "IsWrap": false,
            "IsRowMarginRemoved": false,
            "Columns": [
              {
                "Layout": {
                  "FieldName": "Header",
                  "FontFamily": "",
                  "Color": "",
                  "Name": "",
                  "IsViewOnly": false,
                  "TypeFullName": "Codeer.LowCode.Blazor.Repository.Design.FieldLayoutDesign"
                },
                "Border": "None",
                "HorizontalAlignment": "Center",
                "CanResize": false
              }
            ]
          },
          {
            "IsWrap": false,
            "IsRowMarginRemoved": false,
            "Columns": [
              {
                "Layout": {
                  "FieldName": "ALabel",
                  "FontFamily": "",
                  "Color": "",
                  "Name": "",
                  "IsViewOnly": false,
                  "TypeFullName": "Codeer.LowCode.Blazor.Repository.Design.FieldLayoutDesign"
                },
                "Width": 150,
                "Border": "None",
                "VerticalAlignment": "Middle",
                "CanResize": false
              },
              {
                "Layout": {
                  "FieldName": "A",
                  "FontFamily": "",
                  "Color": "",
                  "Name": "",
                  "IsViewOnly": false,
                  "TypeFullName": "Codeer.LowCode.Blazor.Repository.Design.FieldLayoutDesign"
                },
                "Border": "None",
                "CanResize": false
              }
            ]
          },
          {
            "IsWrap": false,
            "IsRowMarginRemoved": false,
            "Columns": [
              {
                "Layout": {
                  "FieldName": "BLabel",
                  "FontFamily": "",
                  "Color": "",
                  "Name": "",
                  "IsViewOnly": false,
                  "TypeFullName": "Codeer.LowCode.Blazor.Repository.Design.FieldLayoutDesign"
                },
                "Width": 150,
                "Border": "None",
                "VerticalAlignment": "Middle",
                "CanResize": false
              },
              {
                "Layout": {
                  "FieldName": "B",
                  "FontFamily": "",
                  "Color": "",
                  "Name": "",
                  "IsViewOnly": false,
                  "TypeFullName": "Codeer.LowCode.Blazor.Repository.Design.FieldLayoutDesign"
                },
                "Border": "None",
                "CanResize": false
              }
            ]
          },
          {
            "IsWrap": false,
            "IsRowMarginRemoved": false,
            "Columns": [
              {
                "Layout": {
                  "FieldName": "CLabel",
                  "FontFamily": "",
                  "Color": "",
                  "Name": "",
                  "IsViewOnly": false,
                  "TypeFullName": "Codeer.LowCode.Blazor.Repository.Design.FieldLayoutDesign"
                },
                "Width": 150,
                "Border": "None",
                "VerticalAlignment": "Middle",
                "CanResize": false
              },
              {
                "Layout": {
                  "FieldName": "C",
                  "FontFamily": "",
                  "Color": "",
                  "Name": "",
                  "IsViewOnly": false,
                  "TypeFullName": "Codeer.LowCode.Blazor.Repository.Design.FieldLayoutDesign"
                },
                "Border": "None",
                "CanResize": false
              }
            ]
          },
          {
            "IsWrap": false,
            "IsRowMarginRemoved": false,
            "Columns": [
              {
                "Layout": {
                  "FieldName": "Submit",
                  "FontFamily": "",
                  "Color": "",
                  "Name": "",
                  "IsViewOnly": false,
                  "TypeFullName": "Codeer.LowCode.Blazor.Repository.Design.FieldLayoutDesign"
                },
                "Border": "None",
                "HorizontalAlignment": "Center",
                "CanResize": false
              }
            ]
          }
        ],
        "IsViewOnly": false,
        "TypeFullName": "Codeer.LowCode.Blazor.Repository.Design.GridLayoutDesign"
      }
    }
  },
  "ListLayouts": {
    "": {
      "HeaderTitle": "",
      "DataOnlyFields": [],
      "OnBeforeInitialization": "",
      "OnAfterInitialization": "",
      "Elements": [
        [
          {
            "FieldName": "A",
            "Label": "",
            "ColumnSpan": 1,
            "RowSpan": 1,
            "IsViewOnly": false,
            "TextWrap": "Unset",
            "CanResize": false,
            "FontFamily": "",
            "Color": ""
          },
          {
            "FieldName": "B",
            "Label": "",
            "ColumnSpan": 1,
            "RowSpan": 1,
            "IsViewOnly": false,
            "TextWrap": "Unset",
            "CanResize": false,
            "FontFamily": "",
            "Color": ""
          },
          {
            "FieldName": "C",
            "Label": "",
            "ColumnSpan": 1,
            "RowSpan": 1,
            "IsViewOnly": false,
            "TextWrap": "Unset",
            "CanResize": false,
            "FontFamily": "",
            "Color": ""
          }
        ]
      ]
    }
  },
  "SearchLayouts": {
    "": {
      "OnSearchInitialization": "",
      "Layout": {
        "Operator": "And",
        "Name": "SearchGridLayout",
        "IsBordered": false,
        "IsFlowLayout": false,
        "IsFillAvailable": false,
        "IsExpandable": true,
        "ExpanderLabel": "検索条件",
        "IsExpanderDefaultOpened": false,
        "Rows": [
          {
            "IsWrap": false,
            "IsRowMarginRemoved": false,
            "Columns": [
              {
                "Border": "None",
                "CanResize": false
              },
              {
                "Border": "None",
                "CanResize": false
              },
              {
                "Border": "None",
                "CanResize": false
              },
              {
                "Border": "None",
                "CanResize": false
              }
            ]
          }
        ],
        "IsViewOnly": false,
        "TypeFullName": "Codeer.LowCode.Blazor.Repository.Design.SearchGridLayoutDesign"
      }
    }
  },
  "LinkFieldNames": [],
  "ListPageFieldDesign": {
    "LayoutName": "",
    "CanNavigateToDetail": true,
    "DisplayName": "",
    "SearchCondition": {
      "SortFieldVariable": "",
      "SortDescending": false,
      "SelectFields": [],
      "ModuleName": ""
    },
    "PagerPosition": "Bottom",
    "UseIndexSort": false,
    "DeleteTogether": false,
    "CanCreate": false,
    "CanUpdate": false,
    "CanDelete": false,
    "CanSelect": false,
    "OnDataChanged": "",
    "OnSearchDataChanged": "",
    "OnSelectedIndexChanged": "",
    "OnSelectedIndexChanging": "",
    "Name": "",
    "TypeFullName": "Codeer.LowCode.Blazor.Repository.Design.ListFieldDesign"
  }
}